Cyrus/__init__.py
Cyrus/cache.py
Cyrus/client.py
Cyrus/enums.py
Cyrus/key_gen.py
Cyrus/redis.py
Cyrus/types.py
Cyrus/util.py
Cyrus/version.py
Perseus/__init__.py
Perseus/cache.py
Perseus/client.py
Perseus/enums.py
Perseus/key_gen.py
Perseus/redis.py
Perseus/types.py
Perseus/util.py
Perseus/version.py
Cyrus_Kit-0.5.5.dist-info/LICENSE
Cyrus_Kit-0.5.5.dist-info/METADATA
Cyrus_Kit-0.5.5.dist-info/WHEEL
Cyrus_Kit-0.5.5.dist-info/top_level.txt
Cyrus_Kit-0.5.5.dist-info/RECORD
