Metadata-Version: 2.1
Name: Cyrus-Kit
Version: 0.5.5
Summary: Cyrus: Elevate FastAPI with Intelligent Caching by Redis
Home-page: https://github.com/itz-Amethyst/Cyrus
Author: itz-Amethyst
Author-email: pransermi@gmail.com
Maintainer: itz-Amethyst
Maintainer-email: pransermi@gmail.com
License: MIT
Project-URL: Bug Tracker, https://github.com/itz-Amethyst/Cyrus/issues
Project-URL: Source Code, https://github.com/itz-Amethyst/Cyrus
Project-URL: Documentation, https://pypi.org/project/Cyrus
Keywords: Redis,Redis Caching,Redis Connection,Redis client instance
Classifier: Framework :: FastAPI
Classifier: Development Status :: 4 - Beta
Classifier: Intended Audience :: Developers
Classifier: License :: OSI Approved :: MIT License
Classifier: Natural Language :: English
Classifier: Natural Language :: Persian
Classifier: Operating System :: Microsoft :: Windows
Classifier: Operating System :: MacOS :: MacOS X
Classifier: Operating System :: POSIX :: Linux
Classifier: Operating System :: Unix
Classifier: Programming Language :: Python :: 3 :: Only
Classifier: Programming Language :: Python :: 3.7
Classifier: Programming Language :: Python :: 3.8
Classifier: Programming Language :: Python :: 3.9
Classifier: Programming Language :: Python :: 3.10
Classifier: Programming Language :: Python :: 3.11
Requires-Python: >=3.7
License-File: LICENSE
Requires-Dist: fastapi
Requires-Dist: pydantic
Requires-Dist: python-dateutil
Requires-Dist: redis
